plugget_qt/__init__.py
plugget_qt-0.0.8.dist-info/LICENSE
plugget_qt-0.0.8.dist-info/METADATA
plugget_qt-0.0.8.dist-info/WHEEL
plugget_qt-0.0.8.dist-info/top_level.txt
plugget_qt-0.0.8.dist-info/RECORD
