Metadata-Version: 2.1
Name: plugget-qt
Version: 0.0.8
Summary: a qt widget to search for plugget packages
Author: Hannes Delbeke
Project-URL: Homepage, https://github.com/plugget/plugget-qt
Project-URL: Documentation, https://github.com/plugget/plugget-qt
Keywords: dcc,pipeline,qt,widget,plugget,package,manifest,search,installer
Classifier: Programming Language :: Python :: 3.4
Classifier: Programming Language :: Python :: 3.11
Requires-Python: >=3.4
License-File: LICENSE
Requires-Dist: plugget
Requires-Dist: importlib-metadata ; python_version < "3.4"
